version_finder/__init__.py
version_finder/__version__.py
version_finder/common.py
version_finder/git_executer.py
version_finder/logger.py
version_finder/main.py
version_finder/version_finder.py
version_finder_git_based_versions-10.3.2.dist-info/LICENSE
version_finder_git_based_versions-10.3.2.dist-info/METADATA
version_finder_git_based_versions-10.3.2.dist-info/WHEEL
version_finder_git_based_versions-10.3.2.dist-info/entry_points.txt
version_finder_git_based_versions-10.3.2.dist-info/top_level.txt
version_finder_git_based_versions-10.3.2.dist-info/RECORD
